dqv/__init__.py
dqv/data_quality_validation_pydeequ.py
dqv/dqv_pydeequ.py
data_quality_validation_pydeequ-1.2.dist-info/METADATA
data_quality_validation_pydeequ-1.2.dist-info/WHEEL
data_quality_validation_pydeequ-1.2.dist-info/top_level.txt
data_quality_validation_pydeequ-1.2.dist-info/RECORD
